{
  "experiment_name": "One Distance ORACLE CNN",
  "parameters": {
    "window_length": 256,
    "num_examples_per_device": 260000,
    "experiment_name": "One Distance ORACLE CNN",
    "lr": 0.0001,
    "n_epoch": 1000,
    "batch_size": 256,
    "patience": 10,
    "device": "cuda",
    "desired_serial_numbers": [
      "3123D52",
      "3123D65",
      "3123D79",
      "3123D80",
      "3123D54",
      "3123D70",
      "3123D7B",
      "3123D89",
      "3123D58",
      "3123D76",
      "3123D7D",
      "3123EFE",
      "3123D64",
      "3123D78",
      "3123D7E",
      "3124E4A"
    ],
    "seed": 1234,
    "x_net": [
      {
        "class": "Conv1d",
        "kargs": {
          "in_channels": 2,
          "out_channels": 50,
          "kernel_size": 7,
          "stride": 1,
          "padding": 0,
          "groups": 2
        }
      },
      {
        "class": "ReLU",
        "kargs": {
          "inplace": true
        }
      },
      {
        "class": "Conv1d",
        "kargs": {
          "in_channels": 50,
          "out_channels": 50,
          "kernel_size": 7,
          "stride": 1,
          "padding": 0
        }
      },
      {
        "class": "ReLU",
        "kargs": {
          "inplace": true
        }
      },
      {
        "class": "Dropout",
        "kargs": {
          "p": 0.5
        }
      },
      {
        "class": "Flatten",
        "kargs": {}
      },
      {
        "class": "Linear",
        "kargs": {
          "in_features": 5800,
          "out_features": 256
        }
      },
      {
        "class": "ReLU",
        "kargs": {
          "inplace": true
        }
      },
      {
        "class": "Dropout",
        "kargs": {
          "p": 0.5
        }
      },
      {
        "class": "Linear",
        "kargs": {
          "in_features": 256,
          "out_features": 80
        }
      },
      {
        "class": "ReLU",
        "kargs": {
          "inplace": true
        }
      },
      {
        "class": "Dropout",
        "kargs": {
          "p": 0.5
        }
      },
      {
        "class": "Linear",
        "kargs": {
          "in_features": 80,
          "out_features": 16
        }
      }
    ],
    "desired_runs": [
      2
    ],
    "window_stride": 1,
    "source_domains": [
      2
    ],
    "target_domains": [
      2
    ]
  },
  "results": {
    "source_test_label_accuracy": 0.6999118589743589,
    "source_test_label_loss": 0.7359625578073324,
    "target_test_label_accuracy": 0.6999118589743589,
    "target_test_label_loss": 0.7359504485052076,
    "source_val_label_accuracy": 0.6997179487179487,
    "source_val_label_loss": 0.735756933346843,
    "target_val_label_accuracy": 0.6997179487179487,
    "target_val_label_loss": 0.7357557480260913,
    "total_epochs_trained": 156,
    "total_experiment_time_secs": 14007.660426139832,
    "confusion": {
      "2": {
        "6": {
          "4": 22694,
          "6": 48860,
          "10": 5100,
          "14": 930
        },
        "11": {
          "5": 29934,
          "11": 39170,
          "7": 8652,
          "10": 94,
          "8": 144
        },
        "4": {
          "4": 39118,
          "6": 33348,
          "14": 4662,
          "10": 1172
        },
        "14": {
          "4": 464,
          "14": 77408,
          "0": 2
        },
        "8": {
          "8": 76614,
          "7": 1904,
          "5": 34
        },
        "15": {
          "15": 77568,
          "3": 24
        },
        "3": {
          "2": 60766,
          "13": 6810,
          "3": 10658,
          "15": 16
        },
        "10": {
          "10": 63468,
          "6": 14158,
          "11": 148,
          "4": 314,
          "14": 2
        },
        "7": {
          "7": 35188,
          "5": 30934,
          "11": 7942,
          "8": 4812
        },
        "1": {
          "12": 17022,
          "1": 60806,
          "13": 684
        },
        "0": {
          "0": 78122
        },
        "2": {
          "2": 60042,
          "3": 5360,
          "13": 12284,
          "1": 30,
          "12": 2,
          "15": 2
        },
        "9": {
          "9": 77974
        },
        "13": {
          "2": 50750,
          "13": 25286,
          "3": 1018,
          "1": 214
        },
        "12": {
          "12": 66750,
          "1": 10678
        },
        "5": {
          "7": 26216,
          "5": 36216,
          "11": 13930,
          "8": 1498,
          "10": 4
        }
      }
    },
    "per_domain_accuracy": {
      "2": {
        "accuracy": 0.6997179487179487,
        "source?": true
      }
    }
  },
  "history": {
    "epoch_indices": [
      1,
      2,
      3,
      4,
      5,
      6,
      7,
      8,
      9,
      10,
      11,
      12,
      13,
      14,
      15,
      16,
      17,
      18,
      19,
      20,
      21,
      22,
      23,
      24,
      25,
      26,
      27,
      28,
      29,
      30,
      31,
      32,
      33,
      34,
      35,
      36,
      37,
      38,
      39,
      40,
      41,
      42,
      43,
      44,
      45,
      46,
      47,
      48,
      49,
      50,
      51,
      52,
      53,
      54,
      55,
      56,
      57,
      58,
      59,
      60,
      61,
      62,
      63,
      64,
      65,
      66,
      67,
      68,
      69,
      70,
      71,
      72,
      73,
      74,
      75,
      76,
      77,
      78,
      79,
      80,
      81,
      82,
      83,
      84,
      85,
      86,
      87,
      88,
      89,
      90,
      91,
      92,
      93,
      94,
      95,
      96,
      97,
      98,
      99,
      100,
      101,
      102,
      103,
      104,
      105,
      106,
      107,
      108,
      109,
      110,
      111,
      112,
      113,
      114,
      115,
      116,
      117,
      118,
      119,
      120,
      121,
      122,
      123,
      124,
      125,
      126,
      127,
      128,
      129,
      130,
      131,
      132,
      133,
      134,
      135,
      136,
      137,
      138,
      139,
      140,
      141,
      142,
      143,
      144,
      145,
      146,
      147,
      148,
      149,
      150,
      151,
      152,
      153,
      154,
      155,
      156
    ],
    "train_label_loss": [
      2.046099371239379,
      1.7066040608961504,
      1.6496796387682904,
      1.6137993732389513,
      1.5864551810589465,
      1.5649965398704613,
      1.5458216082604377,
      1.5285630754114508,
      1.5119148267180056,
      1.4993508761688903,
      1.4864479930793846,
      1.4740462204755007,
      1.461101948958177,
      1.449184708574316,
      1.4375738757521241,
      1.4258607962786496,
      1.4167259301929684,
      1.40707342843695,
      1.3973252038955688,
      1.3888792747874836,
      1.380719551065466,
      1.3736170501184988,
      1.3655885408736848,
      1.3591768253556975,
      1.3522680317176567,
      1.3462098433945204,
      1.3397904210352636,
      1.3334286277791956,
      1.326568001642332,
      1.322056769999829,
      1.3157318461177114,
      1.3102744813122593,
      1.3042267986339526,
      1.2979744422933557,
      1.290282249398284,
      1.2821926318577357,
      1.2748330950684599,
      1.2678382821764265,
      1.262031881070399,
      1.2565590069005776,
      1.2508469368232475,
      1.245808331133245,
      1.2401096599390218,
      1.2330867230341984,
      1.2278159835102793,
      1.222033995303479,
      1.2161052767156244,
      1.2098010170695546,
      1.204616923059736,
      1.1990765405382429,
      1.1939104941336662,
      1.1899726305007934,
      1.1842247119264289,
      1.1815529488678818,
      1.1773942341175707,
      1.1735565097986997,
      1.169961264861809,
      1.1668328725112664,
      1.1637646877896655,
      1.1609460479767768,
      1.1581436510138459,
      1.1550515602866371,
      1.1524345459152054,
      1.149454951799833,
      1.1467316790098672,
      1.1448923292002835,
      1.14152206495306,
      1.1381757264975663,
      1.1354183831738902,
      1.1315028929762787,
      1.1263387190797827,
      1.1225928625588888,
      1.1194659232778863,
      1.1155917700830398,
      1.1122681422967178,
      1.1083243569594163,
      1.1055427232050634,
      1.1029105406174293,
      1.0993798052242825,
      1.0972776503720125,
      1.0945695204787202,
      1.0931068690635346,
      1.0889074370363256,
      1.0867556083438161,
      1.0842502754127585,
      1.0812693840121175,
      1.0765914541548425,
      1.071734673987378,
      1.066712892967266,
      1.0603863627308017,
      1.0563354036886614,
      1.0524419928854638,
      1.0480692611421858,
      1.0443188866101778,
      1.039946318757403,
      1.0363031834927234,
      1.031827737069392,
      1.028843459868169,
      1.0257481640354618,
      1.0225735860866505,
      1.01961688882178,
      1.0174660508030064,
      1.0137929229788727,
      1.0120186100006103,
      1.0103106833919064,
      1.0077979701377533,
      1.005613114126436,
      1.0035100961203103,
      1.0018504843869052,
      0.9984489783245128,
      0.9974349684138875,
      0.9952923127111498,
      0.992881463936397,
      0.9923439586293566,
      0.9906172466540074,
      0.9897018190740229,
      0.9876498133271605,
      0.9857394000409724,
      0.9853005329697997,
      0.9840567461422511,
      0.9827480145601126,
      0.9816283322114211,
      0.9801210781034533,
      0.9788862231799534,
      0.9779003623920483,
      0.9767107227503599,
      0.9757534269552964,
      0.9744333822386605,
      0.9735008296494956,
      0.9725678233733543,
      0.9717284375337454,
      0.9700001445288187,
      0.9703677791239141,
      0.9689018369245005,
      0.967270607476706,
      0.9661567391615647,
      0.9658294299041832,
      0.9644485029021462,
      0.9628639421201014,
      0.9621501407990088,
      0.9618439699476892,
      0.9604061963374798,
      0.960009818663964,
      0.9592692596100189,
      0.9581236947552189,
      0.957678803726867,
      0.9567060636740464,
      0.9566809550851256,
      0.9554263838097289,
      0.955618382522038,
      0.9547470728119651,
      0.9539182366853232,
      0.9526751475019769,
      0.9521690723503029,
      0.9517407956070952,
      0.9511371388330564
    ],
    "val_label_loss": [
      1.6170360194649043,
      1.533222423849583,
      1.5054591995365214,
      1.4687384887246249,
      1.439687388905548,
      1.4267830264382522,
      1.4017143774658467,
      1.3802152399257914,
      1.3800436114560786,
      1.3602405985522408,
      1.3356613784759528,
      1.3129383647314734,
      1.2939125862250669,
      1.2952736008842036,
      1.2649300002582353,
      1.245207536455253,
      1.2471032838923115,
      1.2293683953516008,
      1.2183590022827193,
      1.2023940210561463,
      1.1818313249512908,
      1.1883858315176021,
      1.16474853801962,
      1.1584355633116041,
      1.158877990449228,
      1.1513645182485166,
      1.134454009178919,
      1.1209933034605037,
      1.1108003209808794,
      1.1112831697491372,
      1.0991390588784238,
      1.1007498120361905,
      1.0833777671372724,
      1.0725200096049008,
      1.0664070580365523,
      1.0606936910926954,
      1.0525319388745944,
      1.0495149569740247,
      1.046089883438381,
      1.0371927002641976,
      1.021545515699011,
      1.023471217990606,
      1.0135615610313573,
      1.007561643388645,
      0.9964517460336834,
      0.9935240084710328,
      1.0122858915444375,
      0.9917205647184186,
      0.9823592478765436,
      1.0001626355028035,
      0.9670590911613711,
      0.9601958586213235,
      0.9648793650954546,
      0.9711203370503073,
      0.9676211286852651,
      0.9532582951530851,
      0.9523767356358169,
      0.9353772497646529,
      0.9415402106078948,
      0.9327300139828918,
      0.9563124760239705,
      0.9263394222433593,
      0.932940551132526,
      0.9208080569821562,
      0.9635496435593738,
      0.9147066736289768,
      0.9166600741843302,
      0.9108032019682063,
      0.9056573345389299,
      0.9115964612381883,
      0.9009604419079641,
      0.8935657832297856,
      0.8886570875472569,
      0.8883883010128466,
      0.8830631336440211,
      0.8766402159439334,
      0.8811033701828213,
      0.872463427844646,
      0.8797446384451446,
      0.8754426126992536,
      0.8713061837410712,
      0.8711198972472409,
      0.8815849211442852,
      0.8645633019513044,
      0.8571579322842323,
      0.8481008889637979,
      0.847493236063933,
      0.8447429173984324,
      0.8368809146652268,
      0.8370748106283277,
      0.838283055013472,
      0.8237044438414147,
      0.8198366975618054,
      0.8226786408393084,
      0.8293771463598356,
      0.8127503910203563,
      0.807344193166157,
      0.8041613601435394,
      0.8023298844829556,
      0.8053319875435129,
      0.7992226399780786,
      0.8041982405541664,
      0.7958206115588484,
      0.7906862204196122,
      0.7932677187080556,
      0.7880807563454719,
      0.8185682659808292,
      0.7873090861076405,
      0.7916136688390064,
      0.7803703443108277,
      0.7793718700627991,
      0.7848265464184615,
      0.7723702270051708,
      0.7747592721638668,
      0.7694185829680898,
      0.7934111038664504,
      0.7702806491261138,
      0.7708729337091031,
      0.7658103443346032,
      0.7806870239841048,
      0.7694964965070438,
      0.7759342923625949,
      0.7629344407606555,
      0.7618670828817711,
      0.7798469337016662,
      0.7550457835295241,
      0.7604851500972359,
      0.7772094780935236,
      0.767603158437394,
      0.7574995038350945,
      0.7619912803564236,
      0.7592808514271142,
      0.7669796681824622,
      0.7585438286260663,
      0.7568830016502305,
      0.7534938260753982,
      0.7533126813989863,
      0.7484174991260306,
      0.7523504275831656,
      0.7467819455464029,
      0.7535763184392521,
      0.7644938999409554,
      0.7464340002787123,
      0.7455714742016656,
      0.7357619831902361,
      0.7413285277337691,
      0.7563496316134489,
      0.7409106674401656,
      0.742101547144005,
      0.7407538001658586,
      0.7477728050932521,
      0.736441808391341,
      0.7421293492147041,
      0.7443020642292705,
      0.746014581683036,
      0.7388641608846882
    ]
  }
}