{
  "experiment_name": "One Distance ORACLE CNN",
  "parameters": {
    "window_length": 256,
    "experiment_name": "One Distance ORACLE CNN",
    "lr": 0.0001,
    "n_epoch": 1000,
    "batch_size": 256,
    "patience": 10,
    "device": "cuda",
    "desired_serial_numbers": [
      "3123D52",
      "3123D65",
      "3123D79",
      "3123D80",
      "3123D54",
      "3123D70",
      "3123D7B",
      "3123D89",
      "3123D58",
      "3123D76",
      "3123D7D",
      "3123EFE",
      "3123D64",
      "3123D78",
      "3123D7E",
      "3124E4A"
    ],
    "seed": 1234,
    "x_net": [
      {
        "class": "Conv1d",
        "kargs": {
          "in_channels": 2,
          "out_channels": 50,
          "kernel_size": 7,
          "stride": 1,
          "padding": 0,
          "groups": 2
        }
      },
      {
        "class": "ReLU",
        "kargs": {
          "inplace": true
        }
      },
      {
        "class": "Conv1d",
        "kargs": {
          "in_channels": 50,
          "out_channels": 50,
          "kernel_size": 7,
          "stride": 1,
          "padding": 0
        }
      },
      {
        "class": "ReLU",
        "kargs": {
          "inplace": true
        }
      },
      {
        "class": "Dropout",
        "kargs": {
          "p": 0.5
        }
      },
      {
        "class": "Flatten",
        "kargs": {}
      },
      {
        "class": "Linear",
        "kargs": {
          "in_features": 5800,
          "out_features": 256
        }
      },
      {
        "class": "ReLU",
        "kargs": {
          "inplace": true
        }
      },
      {
        "class": "Dropout",
        "kargs": {
          "p": 0.5
        }
      },
      {
        "class": "Linear",
        "kargs": {
          "in_features": 256,
          "out_features": 80
        }
      },
      {
        "class": "ReLU",
        "kargs": {
          "inplace": true
        }
      },
      {
        "class": "Dropout",
        "kargs": {
          "p": 0.5
        }
      },
      {
        "class": "Linear",
        "kargs": {
          "in_features": 80,
          "out_features": 17
        }
      }
    ],
    "desired_runs": [
      2
    ],
    "window_stride": 1,
    "source_domains": [
      20
    ],
    "target_domains": [
      20
    ],
    "num_examples_per_device": 130000
  },
  "results": {
    "source_test_label_accuracy": 0.4667980769230769,
    "source_test_label_loss": 1.4189143594510247,
    "target_test_label_accuracy": 0.4667980769230769,
    "target_test_label_loss": 1.4189193193006946,
    "source_val_label_accuracy": 0.4670096153846154,
    "source_val_label_loss": 1.417349153801102,
    "target_val_label_accuracy": 0.4670096153846154,
    "target_val_label_loss": 1.4173297924130934,
    "total_epochs_trained": 390,
    "total_experiment_time_secs": 17482.736224412918,
    "confusion": {
      "20": {
        "2": {
          "2": 14572,
          "5": 5130,
          "9": 9064,
          "1": 3476,
          "7": 1864,
          "4": 1196,
          "15": 3182,
          "3": 334,
          "6": 54
        },
        "3": {
          "9": 7584,
          "2": 5162,
          "4": 6706,
          "5": 1786,
          "15": 6324,
          "6": 1906,
          "7": 7810,
          "1": 630,
          "13": 274,
          "3": 504,
          "10": 26,
          "12": 14
        },
        "8": {
          "8": 21852,
          "0": 6512,
          "14": 9084,
          "11": 1522,
          "1": 74
        },
        "11": {
          "11": 35640,
          "8": 308,
          "0": 3316,
          "14": 2
        },
        "14": {
          "8": 10802,
          "11": 184,
          "14": 25202,
          "1": 1710,
          "0": 1364,
          "5": 42,
          "9": 2
        },
        "5": {
          "5": 7844,
          "2": 10676,
          "1": 12758,
          "15": 988,
          "4": 816,
          "9": 4124,
          "14": 614,
          "7": 854,
          "3": 190,
          "6": 76,
          "8": 20,
          "13": 8,
          "0": 8,
          "11": 2
        },
        "0": {
          "0": 14666,
          "8": 10538,
          "11": 12420,
          "14": 1318,
          "1": 92
        },
        "6": {
          "6": 19566,
          "7": 3444,
          "10": 3436,
          "4": 8918,
          "13": 1004,
          "12": 1114,
          "9": 404,
          "15": 934,
          "3": 58,
          "2": 58,
          "5": 8
        },
        "4": {
          "4": 15184,
          "6": 12186,
          "15": 1956,
          "7": 6820,
          "13": 408,
          "9": 1536,
          "10": 606,
          "3": 240,
          "2": 158,
          "12": 152,
          "5": 46
        },
        "7": {
          "15": 6814,
          "4": 11298,
          "9": 4056,
          "6": 4282,
          "7": 10748,
          "2": 438,
          "10": 70,
          "13": 444,
          "3": 350,
          "5": 68,
          "12": 40,
          "1": 4
        },
        "9": {
          "4": 3430,
          "9": 12210,
          "2": 7998,
          "7": 5256,
          "15": 7714,
          "5": 1430,
          "3": 512,
          "1": 342,
          "6": 214,
          "13": 14
        },
        "1": {
          "1": 30134,
          "5": 4304,
          "9": 376,
          "2": 3456,
          "14": 910,
          "7": 16,
          "4": 36,
          "15": 16,
          "0": 8,
          "3": 10,
          "8": 12
        },
        "13": {
          "13": 27564,
          "12": 9134,
          "10": 940,
          "6": 632,
          "7": 100,
          "15": 214,
          "4": 10
        },
        "15": {
          "9": 7342,
          "15": 13256,
          "7": 6050,
          "13": 1420,
          "2": 4974,
          "3": 224,
          "1": 320,
          "6": 1650,
          "4": 2862,
          "12": 150,
          "5": 644,
          "10": 102
        },
        "12": {
          "13": 11916,
          "12": 20850,
          "10": 5880,
          "6": 340,
          "7": 12,
          "15": 6,
          "4": 2,
          "9": 2
        },
        "10": {
          "6": 3932,
          "10": 21622,
          "12": 11530,
          "13": 1708,
          "15": 18,
          "4": 58,
          "7": 64
        }
      }
    },
    "per_domain_accuracy": {
      "20": {
        "accuracy": 0.4670096153846154,
        "source?": true
      }
    }
  },
  "history": {
    "epoch_indices": [
      1,
      2,
      3,
      4,
      5,
      6,
      7,
      8,
      9,
      10,
      11,
      12,
      13,
      14,
      15,
      16,
      17,
      18,
      19,
      20,
      21,
      22,
      23,
      24,
      25,
      26,
      27,
      28,
      29,
      30,
      31,
      32,
      33,
      34,
      35,
      36,
      37,
      38,
      39,
      40,
      41,
      42,
      43,
      44,
      45,
      46,
      47,
      48,
      49,
      50,
      51,
      52,
      53,
      54,
      55,
      56,
      57,
      58,
      59,
      60,
      61,
      62,
      63,
      64,
      65,
      66,
      67,
      68,
      69,
      70,
      71,
      72,
      73,
      74,
      75,
      76,
      77,
      78,
      79,
      80,
      81,
      82,
      83,
      84,
      85,
      86,
      87,
      88,
      89,
      90,
      91,
      92,
      93,
      94,
      95,
      96,
      97,
      98,
      99,
      100,
      101,
      102,
      103,
      104,
      105,
      106,
      107,
      108,
      109,
      110,
      111,
      112,
      113,
      114,
      115,
      116,
      117,
      118,
      119,
      120,
      121,
      122,
      123,
      124,
      125,
      126,
      127,
      128,
      129,
      130,
      131,
      132,
      133,
      134,
      135,
      136,
      137,
      138,
      139,
      140,
      141,
      142,
      143,
      144,
      145,
      146,
      147,
      148,
      149,
      150,
      151,
      152,
      153,
      154,
      155,
      156,
      157,
      158,
      159,
      160,
      161,
      162,
      163,
      164,
      165,
      166,
      167,
      168,
      169,
      170,
      171,
      172,
      173,
      174,
      175,
      176,
      177,
      178,
      179,
      180,
      181,
      182,
      183,
      184,
      185,
      186,
      187,
      188,
      189,
      190,
      191,
      192,
      193,
      194,
      195,
      196,
      197,
      198,
      199,
      200,
      201,
      202,
      203,
      204,
      205,
      206,
      207,
      208,
      209,
      210,
      211,
      212,
      213,
      214,
      215,
      216,
      217,
      218,
      219,
      220,
      221,
      222,
      223,
      224,
      225,
      226,
      227,
      228,
      229,
      230,
      231,
      232,
      233,
      234,
      235,
      236,
      237,
      238,
      239,
      240,
      241,
      242,
      243,
      244,
      245,
      246,
      247,
      248,
      249,
      250,
      251,
      252,
      253,
      254,
      255,
      256,
      257,
      258,
      259,
      260,
      261,
      262,
      263,
      264,
      265,
      266,
      267,
      268,
      269,
      270,
      271,
      272,
      273,
      274,
      275,
      276,
      277,
      278,
      279,
      280,
      281,
      282,
      283,
      284,
      285,
      286,
      287,
      288,
      289,
      290,
      291,
      292,
      293,
      294,
      295,
      296,
      297,
      298,
      299,
      300,
      301,
      302,
      303,
      304,
      305,
      306,
      307,
      308,
      309,
      310,
      311,
      312,
      313,
      314,
      315,
      316,
      317,
      318,
      319,
      320,
      321,
      322,
      323,
      324,
      325,
      326,
      327,
      328,
      329,
      330,
      331,
      332,
      333,
      334,
      335,
      336,
      337,
      338,
      339,
      340,
      341,
      342,
      343,
      344,
      345,
      346,
      347,
      348,
      349,
      350,
      351,
      352,
      353,
      354,
      355,
      356,
      357,
      358,
      359,
      360,
      361,
      362,
      363,
      364,
      365,
      366,
      367,
      368,
      369,
      370,
      371,
      372,
      373,
      374,
      375,
      376,
      377,
      378,
      379,
      380,
      381,
      382,
      383,
      384,
      385,
      386,
      387,
      388,
      389,
      390
    ],
    "train_label_loss": [
      2.775164235660966,
      2.77288238614085,
      2.772750368433495,
      2.7726893699957182,
      2.689947395846143,
      2.3438383625445653,
      2.275121108431018,
      2.236326226663321,
      2.2111213220658015,
      2.1913214338060505,
      2.17563413022775,
      2.1600755262182063,
      2.1475036208807334,
      2.1361134872154848,
      2.1245017247654383,
      2.1149788495315613,
      2.103803697077534,
      2.097591033506662,
      2.091833428302898,
      2.084972870584614,
      2.0800902157938093,
      2.075298466679081,
      2.068692361461798,
      2.0659960892297717,
      2.0612649151376865,
      2.0568106535995057,
      2.0524061455714886,
      2.0499104123494463,
      2.046672361016106,
      2.0433340823977306,
      2.039622357311631,
      2.0372771741887856,
      2.035093026091613,
      2.0319164697547167,
      2.0288233723905353,
      2.0261696391803135,
      2.0246898646763776,
      2.022126149401886,
      2.0202336878045535,
      2.015310929294377,
      2.011675519363119,
      2.009888481112975,
      2.00659288654599,
      2.0036313737075875,
      1.9991960266471411,
      1.9973066514135245,
      1.995235535980277,
      1.9923672609649463,
      1.9916094696429543,
      1.987618192192036,
      1.9859464167081522,
      1.9835021999650195,
      1.980808091922316,
      1.978806633842813,
      1.9769648893640681,
      1.9738948496920483,
      1.9730097907379207,
      1.9703701013586525,
      1.9699178485595392,
      1.967780595171133,
      1.9656988931020771,
      1.9634371086347286,
      1.9615203793751372,
      1.9616941288637544,
      1.959571071838863,
      1.95932740071571,
      1.9567364340676872,
      1.9546622465012278,
      1.9530312003549477,
      1.9519364541048072,
      1.9502833194496259,
      1.9480430767799397,
      1.9464323811767474,
      1.9463381461914413,
      1.9447127924354435,
      1.9430441309170046,
      1.9418769185385456,
      1.9405240862094568,
      1.9391601952487072,
      1.9378858169674371,
      1.93669458161175,
      1.9350246307970602,
      1.9338280315053782,
      1.9328118678386705,
      1.9298068455377209,
      1.9291637910192023,
      1.927528926633749,
      1.9277714905230807,
      1.9255972795932437,
      1.9245630176384239,
      1.9230470915761175,
      1.9225264647045552,
      1.92202736998996,
      1.9191221663971993,
      1.9188726602224357,
      1.9175572477061034,
      1.9166029393253783,
      1.9138527881202148,
      1.9130733052763758,
      1.9120780923279361,
      1.9108059494723415,
      1.909482121174178,
      1.9084690596106686,
      1.906652174041241,
      1.904201695666702,
      1.9037447970376236,
      1.9009552911950902,
      1.898863635401853,
      1.8988136922843681,
      1.8956873597139716,
      1.8940311742608558,
      1.8913556170111467,
      1.8902975003721008,
      1.8868502859869754,
      1.8863837862945307,
      1.883354215409853,
      1.8819557904945647,
      1.8802195649735536,
      1.8785424934157842,
      1.8765649137659584,
      1.8747499388984488,
      1.8732917973805747,
      1.8718256041428543,
      1.8704501795995085,
      1.8671534079874954,
      1.865962931123967,
      1.8643352450742667,
      1.8629468689907116,
      1.8611014871406153,
      1.8584121512000236,
      1.8571113660701049,
      1.856228303054214,
      1.8534197487492434,
      1.85215988799238,
      1.8507544017500348,
      1.8477910099401755,
      1.8475163013120242,
      1.8452334798002712,
      1.843978839689334,
      1.8426158912532273,
      1.8398982388938026,
      1.838651642832072,
      1.8374729356014612,
      1.8342095986323015,
      1.8337773119430838,
      1.832320416254501,
      1.8319514345812562,
      1.8297493314231665,
      1.8281101665961257,
      1.826736059223214,
      1.8260124610991082,
      1.8227290357299326,
      1.8219312723259717,
      1.8204841007034487,
      1.82014571564107,
      1.8180656820200332,
      1.8164557752771888,
      1.8153407818908933,
      1.8138592110530234,
      1.8130060074492012,
      1.8113634791094206,
      1.8094835179306452,
      1.8090176946796612,
      1.807245244540578,
      1.8070213589319533,
      1.8060511366769398,
      1.804834281949722,
      1.803562282048868,
      1.8017880832972908,
      1.8031555610576595,
      1.8002064558985196,
      1.8011004432889144,
      1.799146678796465,
      1.7993129712494114,
      1.7958404496207352,
      1.7967158658259696,
      1.7965568788402024,
      1.7943481576174456,
      1.7953707935018715,
      1.7937000532190508,
      1.792667036443823,
      1.7917782474209656,
      1.7913126304179807,
      1.789664567019869,
      1.7897410216085015,
      1.7888108325490804,
      1.7865516439226945,
      1.7859262112952485,
      1.7851029122051811,
      1.7848251889736173,
      1.7844101967271706,
      1.7830741843300362,
      1.7818925734268798,
      1.7813939935253977,
      1.7801083944392104,
      1.7798581272363663,
      1.7787253449025202,
      1.778681013109647,
      1.7781776199025612,
      1.7764590456557845,
      1.7770913278293676,
      1.775620456088109,
      1.7743771201321847,
      1.7762144815527772,
      1.7731271567852689,
      1.7745664956574703,
      1.773433479473896,
      1.7729883579597527,
      1.7715039788922178,
      1.7704369503527921,
      1.7704860988883866,
      1.7701139487797701,
      1.7702422831548081,
      1.7688025455979524,
      1.7687450628701478,
      1.768570513916418,
      1.7675899695578843,
      1.766487726661391,
      1.767761400731807,
      1.7662596054762896,
      1.7662462591286618,
      1.7657307990199236,
      1.7659780741282824,
      1.7651344676267582,
      1.7651577423603055,
      1.7636238757400406,
      1.764196234979207,
      1.7627767475135887,
      1.762223449248805,
      1.7616113995197955,
      1.7612608974660666,
      1.7605038962619046,
      1.7604636101866908,
      1.7606700798797876,
      1.759529271101482,
      1.7590584195573957,
      1.7592055426200566,
      1.758351261396113,
      1.7580495802829705,
      1.7575917897428976,
      1.7578508062117881,
      1.7577721541315192,
      1.7574038810074413,
      1.7566296638064243,
      1.7566222266180103,
      1.754975641830058,
      1.754935946687532,
      1.7560153849181914,
      1.7542508720680967,
      1.752289508968466,
      1.7543204359909317,
      1.7523992874786656,
      1.752825485356414,
      1.7529494458948343,
      1.7522780613976356,
      1.751983652197862,
      1.7521493342690662,
      1.752259303036286,
      1.7519388782324168,
      1.7509118694335264,
      1.7503297033231133,
      1.751342062876362,
      1.749682860346786,
      1.7482365667819977,
      1.7493024634199974,
      1.7487583894350693,
      1.7497935664595095,
      1.7464874920378926,
      1.747457445925298,
      1.7483786237432652,
      1.7475791523225197,
      1.747347199401272,
      1.7462892789294113,
      1.746701322925577,
      1.7462415878782795,
      1.7470152520387316,
      1.7445225381566167,
      1.7457107227143691,
      1.744882353624714,
      1.7441956776648802,
      1.7432231826579352,
      1.7445363102876352,
      1.7431409355624987,
      1.7423395819427594,
      1.7432291570175884,
      1.7433340506714607,
      1.740352246182042,
      1.7390045678942516,
      1.738195254623303,
      1.7349477875584791,
      1.7331577236181237,
      1.728008243374516,
      1.727348446594512,
      1.7253597420437259,
      1.7251106774547096,
      1.7219759266713501,
      1.7232404266354404,
      1.7210771134005318,
      1.7195965697367985,
      1.7181641376680798,
      1.717301560269797,
      1.7173992781447962,
      1.7157748630571634,
      1.7152941542168039,
      1.7139771850425987,
      1.7132588486421627,
      1.7125447939049174,
      1.7110643362529503,
      1.711191061700782,
      1.7109831670500892,
      1.7095806942375065,
      1.7078081244070988,
      1.7067418364616722,
      1.706281499017643,
      1.7051684081386749,
      1.703243658805866,
      1.7024469647855196,
      1.6978392433348923,
      1.6975733513109459,
      1.6949195087836262,
      1.6951257839442642,
      1.6931816043774957,
      1.6924036037066819,
      1.6919051642868925,
      1.6900378948315957,
      1.690901985588456,
      1.6891882394646123,
      1.6873990633903508,
      1.6870013309011311,
      1.6860673762071987,
      1.6857741517440512,
      1.6854790257376457,
      1.6840347888474727,
      1.684100692764281,
      1.683181707638561,
      1.6824883346441928,
      1.6816899527686893,
      1.6804734954476859,
      1.680501739372684,
      1.6807560948589515,
      1.6800562496678235,
      1.679977935179544,
      1.678646898114564,
      1.6775935806134918,
      1.677814202763025,
      1.6764109905720093,
      1.6760361063413312,
      1.6752849660300337,
      1.6747361212214338,
      1.6753050598372219,
      1.6744403989590002,
      1.673723755799936,
      1.6726349145593187,
      1.6730974456806222,
      1.6714521896319383,
      1.6722189877522813,
      1.6716819352322323,
      1.6706967197054716,
      1.6705964755911364,
      1.6711059097625032,
      1.6696747715588864,
      1.6683993512651925,
      1.6689545882947,
      1.6675840505777364,
      1.6677052505240997,
      1.6674673752191198,
      1.6668945464152325,
      1.666675581585003,
      1.6659223020873157,
      1.6654634722384052,
      1.6641559517417108,
      1.6641594207362285,
      1.6644574580229452,
      1.6631667031140267,
      1.6630592276401157,
      1.6617672218091042,
      1.6632823003076131,
      1.6614611188654491,
      1.6614224380707439,
      1.6614388056235643,
      1.6614325731866972,
      1.6605286584163685,
      1.6598011862418487,
      1.6593016880222513,
      1.6593596735751746,
      1.6593018724738964,
      1.6590991898763363,
      1.6586417266169011,
      1.6575020986141535,
      1.6558900623465724
    ],
    "val_label_loss": [
      2.772785223733215,
      2.7726441984591275,
      2.7727767857887198,
      2.7726110125096532,
      2.353521561016305,
      2.231841045877208,
      2.15935745035849,
      2.1368882223853722,
      2.120132291972197,
      2.0837302467097407,
      2.0885850765159426,
      2.0842037238088955,
      2.056544648808862,
      2.033283162938463,
      2.0361492354132484,
      2.0430115494599,
      2.002357069149283,
      1.9987567760007512,
      1.9913203113875104,
      2.005106254617536,
      1.9958068768053001,
      2.0033724980827627,
      1.9724776300863716,
      1.967753668903229,
      1.9618408563588856,
      1.9546198837086253,
      1.9504221809800284,
      1.9544376707937603,
      1.9436524727972342,
      1.9419996486128697,
      1.9363753020127745,
      1.9773923940987153,
      1.9302588111558245,
      1.926454563919299,
      1.94178438822298,
      1.9202479282493372,
      1.94205988372712,
      1.9145484012692946,
      1.9426166158508726,
      2.0107945975365453,
      1.901632859435015,
      1.9537006205863108,
      1.913372234011205,
      1.9466882761234725,
      1.8873136045504437,
      2.0261733904542054,
      1.8797624235372254,
      1.8824601641827865,
      1.8854854605645797,
      1.8787811586757093,
      1.869181920506115,
      1.8694133330212939,
      1.8636575957807584,
      1.8724151161286164,
      1.8559500910983504,
      1.8626702423463404,
      1.8549084110862413,
      1.8445750033884776,
      1.8441560082595987,
      1.8405074334907374,
      1.834443022033247,
      1.8511697059776864,
      1.8461617102282668,
      1.888363531517924,
      1.8344267649764012,
      1.8293988099344642,
      1.8509480500436397,
      1.8235223173997361,
      1.822616142362136,
      1.8403195701142234,
      1.814907924673223,
      1.81721550006178,
      1.8124347689505773,
      1.810082336152744,
      1.8860600200024074,
      1.8313426213542197,
      1.8016250736895303,
      1.8019390325256799,
      1.8071491936369937,
      1.8166353759264926,
      1.7969102882967316,
      1.8114468135043575,
      1.810126414154278,
      1.791427331346288,
      1.7909746671720448,
      1.7863411262839226,
      1.7917787377417724,
      1.8005247330254859,
      1.7855291298122264,
      1.7800013862544146,
      1.7783038986814717,
      1.7796082835983702,
      1.7989894106702984,
      1.7747140221169388,
      1.8081196600340546,
      1.7688136198561732,
      1.8341032801542838,
      1.7689871351869504,
      1.7647142757442371,
      1.7812777610955617,
      1.7636276803317865,
      1.7640141298577274,
      1.807195117866729,
      1.7516241951786757,
      1.7751207111114553,
      1.7519608743861623,
      1.745017134527186,
      1.7663341156276549,
      1.7474445892808084,
      1.7750087838567996,
      1.7328690649350222,
      1.7358444315962755,
      1.7346979330757586,
      1.7394269770339827,
      1.723053341424299,
      1.719600694701748,
      1.743571198211526,
      1.7329888662615205,
      1.7586430410951548,
      1.7214994168457582,
      1.7057984218527,
      1.6970077967233008,
      1.715445959147515,
      1.696522478494026,
      1.6976727626673798,
      1.702367653604215,
      1.7112090783201348,
      1.6884937169025724,
      1.6843877652319266,
      1.6835996641107422,
      1.6858759124910763,
      1.7345776190221847,
      1.66943550608606,
      1.6931702422743649,
      1.6733209140189267,
      1.6633513388426409,
      1.6587246814842005,
      1.6557476337666,
      1.6516019458942868,
      1.652458313061039,
      1.646717796372624,
      1.6761658921214377,
      1.6488200603106453,
      1.642317826577735,
      1.650665659998361,
      1.683146873881721,
      1.709779002805339,
      1.6879766766803983,
      1.6392710912022266,
      1.6309682077027619,
      1.624234701591598,
      1.6225444650532672,
      1.6329898635709355,
      1.6253938151735865,
      1.6173007142064608,
      1.7332542195879503,
      1.613898370381356,
      1.6289369584694566,
      1.6054091848634715,
      1.6033941760622545,
      1.600746213265185,
      1.6393768630915728,
      1.6005408187886552,
      1.6087777280142506,
      1.6018238678831267,
      1.5964284781259626,
      1.5902267275920552,
      1.6244316139213368,
      1.599758257525587,
      1.5930043302470294,
      1.5892146230232922,
      1.6031247196479153,
      1.5932934447523999,
      1.5970819248734585,
      1.6033899557209093,
      1.5910628479557805,
      1.5866694760381246,
      1.574474546926935,
      1.5869347191521923,
      1.5804622021730657,
      1.5960297382102822,
      1.5917509714045224,
      1.574539889948988,
      1.5851378352843513,
      1.5925592782558038,
      1.576119769881063,
      1.6235692530405923,
      1.5679957137135232,
      1.5698032380128317,
      1.5640107035343525,
      1.6328843359677296,
      1.5659697359951918,
      1.5623981574209524,
      1.5782380572491927,
      1.55772649703992,
      1.5817935760144428,
      1.5557841980819138,
      1.5762404472344815,
      1.568205818766155,
      1.5549435784720904,
      1.5531124640332568,
      1.5598840230405087,
      1.5505418498756653,
      1.565524452822046,
      1.5628804971782568,
      1.552449491202,
      1.567152538291737,
      1.5537982264730752,
      1.5489982904421686,
      1.5710578343240427,
      1.5526193508464259,
      1.6062928800997527,
      1.5852790691502472,
      1.55226723848551,
      1.550437088282603,
      1.5640461344128265,
      1.5528555769134096,
      1.5542192033708242,
      1.541528051656421,
      1.5383288878901655,
      1.5447272333187387,
      1.5452587780549547,
      1.566910067183547,
      1.5501321989361432,
      1.5502497954286445,
      1.5418639241720047,
      1.5500565161951454,
      1.537800291603564,
      1.5390098855767316,
      1.5317872016521825,
      1.5471449910469774,
      1.5304316548268457,
      1.5401988811821503,
      1.532834824526085,
      1.5904169305608935,
      1.5394217627668498,
      1.5596391221751338,
      1.5626774746634318,
      1.5416667531806,
      1.537217440519106,
      1.54999940438384,
      1.5293400110623405,
      1.5457639838947048,
      1.5519712029958572,
      1.5397396032882578,
      1.5383702105826487,
      1.5351949726782244,
      1.5253700900019145,
      1.5321548280410828,
      1.5285711946596954,
      1.5293651684275213,
      1.5263812452970322,
      1.5244796421803637,
      1.5463841108145335,
      1.5335820722619073,
      1.5206682287932811,
      1.5427741166311175,
      1.5219513461470506,
      1.5188662141341474,
      1.5373964340986044,
      1.5297749991100082,
      1.5260726222256542,
      1.5246543877431855,
      1.5294302606113237,
      1.5174138029644586,
      1.5176045534745701,
      1.5412324939818536,
      1.520869000511545,
      1.5481073293067864,
      1.5208642384964879,
      1.517908490320226,
      1.515399863721896,
      1.5280689580994027,
      1.531539217970037,
      1.5201565643330888,
      1.5206834036762154,
      1.539542588667365,
      1.5306929632520168,
      1.5166731672858096,
      1.5588604790739977,
      1.5182684425255428,
      1.5175326012313317,
      1.5129810276336608,
      1.518073578072533,
      1.5167107944903166,
      1.510699013102925,
      1.5231140813835338,
      1.506615441387261,
      1.5162945262128158,
      1.5072159221467667,
      1.5037194646901044,
      1.5055886876690672,
      1.4961443961497893,
      1.4943480184569136,
      1.4950878543869406,
      1.507085047362768,
      1.4980938436556683,
      1.512922046221701,
      1.4907215385773418,
      1.4884270327906808,
      1.4981900889722903,
      1.5070963835892275,
      1.4978002303931632,
      1.4914631938425804,
      1.4880839931466132,
      1.4813233313744336,
      1.4950068368590983,
      1.506899588023961,
      1.4805281073270615,
      1.487416226517675,
      1.4780259548982115,
      1.4800192896120856,
      1.4839081965674135,
      1.4753688151372857,
      1.4991099234972947,
      1.4725842516964043,
      1.4829227157652232,
      1.4684499751553368,
      1.475984434009674,
      1.464815756842384,
      1.4693159614066984,
      1.468285089442728,
      1.4718219862305013,
      1.4671555586385374,
      1.4711564012586924,
      1.5031391616919865,
      1.4585257506546572,
      1.4559970921038408,
      1.457530988250432,
      1.4837076017561264,
      1.4521223077820988,
      1.4527756001149366,
      1.4688607954020574,
      1.4565130905404846,
      1.450839183582841,
      1.4585238556279032,
      1.4552689702712287,
      1.4643158119559974,
      1.4493606643074355,
      1.4516480048236737,
      1.4609903781701543,
      1.4491144748277798,
      1.4547065959982055,
      1.4766669232303535,
      1.4584590524215009,
      1.4422296957465055,
      1.4534168605241158,
      1.4428158585804227,
      1.4423322100635432,
      1.445661101603332,
      1.4448491902112766,
      1.4412904045834123,
      1.437892684983464,
      1.4358913882821187,
      1.4370480626210314,
      1.4622960111173673,
      1.4466124494316346,
      1.4456181663093848,
      1.431715040836694,
      1.4403382063498744,
      1.431941076318586,
      1.4272969798830515,
      1.4425323122930487,
      1.4299775556622225,
      1.4575422409619339,
      1.450802916674657,
      1.4269321187780566,
      1.4262856565800919,
      1.430983553273058,
      1.4369867118877695,
      1.4235653059711408,
      1.4512604632467594,
      1.4259035018157333,
      1.4225785076080335,
      1.4293542750259225,
      1.4450049467806547,
      1.4344623522058289,
      1.4357418378324562,
      1.4173522044440778,
      1.4323362154096144,
      1.4184855947345862,
      1.4186522839399907,
      1.4332465601319462,
      1.4183698422210542,
      1.4207874626483556,
      1.4709609238410994,
      1.445078190474162,
      1.4178195220706304,
      1.4180865620275909,
      1.4217551061616167
    ]
  }
}