{
  "experiment_name": "One Distance ORACLE CNN",
  "parameters": {
    "window_length": 256,
    "num_examples_per_device": 260000,
    "experiment_name": "One Distance ORACLE CNN",
    "lr": 0.0001,
    "n_epoch": 1000,
    "batch_size": 256,
    "patience": 10,
    "device": "cuda",
    "desired_serial_numbers": [
      "3123D52",
      "3123D65",
      "3123D79",
      "3123D80",
      "3123D54",
      "3123D70",
      "3123D7B",
      "3123D89",
      "3123D58",
      "3123D76",
      "3123D7D",
      "3123EFE",
      "3123D64",
      "3123D78",
      "3123D7E",
      "3124E4A"
    ],
    "seed": 82,
    "x_net": [
      {
        "class": "Conv1d",
        "kargs": {
          "in_channels": 2,
          "out_channels": 50,
          "kernel_size": 7,
          "stride": 1,
          "padding": 0,
          "groups": 2
        }
      },
      {
        "class": "ReLU",
        "kargs": {
          "inplace": true
        }
      },
      {
        "class": "Conv1d",
        "kargs": {
          "in_channels": 50,
          "out_channels": 50,
          "kernel_size": 7,
          "stride": 1,
          "padding": 0
        }
      },
      {
        "class": "ReLU",
        "kargs": {
          "inplace": true
        }
      },
      {
        "class": "Dropout",
        "kargs": {
          "p": 0.5
        }
      },
      {
        "class": "Flatten",
        "kargs": {}
      },
      {
        "class": "Linear",
        "kargs": {
          "in_features": 5800,
          "out_features": 256
        }
      },
      {
        "class": "ReLU",
        "kargs": {
          "inplace": true
        }
      },
      {
        "class": "Dropout",
        "kargs": {
          "p": 0.5
        }
      },
      {
        "class": "Linear",
        "kargs": {
          "in_features": 256,
          "out_features": 80
        }
      },
      {
        "class": "ReLU",
        "kargs": {
          "inplace": true
        }
      },
      {
        "class": "Dropout",
        "kargs": {
          "p": 0.5
        }
      },
      {
        "class": "Linear",
        "kargs": {
          "in_features": 80,
          "out_features": 16
        }
      }
    ],
    "desired_runs": [
      1
    ],
    "window_stride": 1,
    "source_domains": [
      2
    ],
    "target_domains": [
      2
    ]
  },
  "results": {
    "source_test_label_accuracy": 0.6948141025641026,
    "source_test_label_loss": 0.8674276639341428,
    "target_test_label_accuracy": 0.6948141025641026,
    "target_test_label_loss": 0.8674518808759168,
    "source_val_label_accuracy": 0.6947083333333334,
    "source_val_label_loss": 0.8665223344121437,
    "target_val_label_accuracy": 0.6947083333333334,
    "target_val_label_loss": 0.8665273093463359,
    "total_epochs_trained": 187,
    "total_experiment_time_secs": 16985.726415395737,
    "confusion": {
      "2": {
        "13": {
          "13": 50294,
          "3": 24978,
          "2": 2814,
          "15": 60,
          "1": 84
        },
        "6": {
          "6": 34190,
          "14": 42950,
          "4": 594,
          "0": 2
        },
        "1": {
          "1": 70370,
          "3": 6286,
          "12": 1028,
          "13": 2
        },
        "8": {
          "8": 71018,
          "5": 7066,
          "7": 2,
          "12": 14
        },
        "15": {
          "15": 78278,
          "13": 20,
          "2": 94,
          "3": 2,
          "9": 10
        },
        "2": {
          "2": 8626,
          "1": 18222,
          "13": 25758,
          "15": 8860,
          "3": 15886,
          "12": 808,
          "8": 6,
          "5": 4,
          "7": 2
        },
        "7": {
          "7": 37784,
          "11": 34978,
          "5": 5348,
          "4": 516
        },
        "5": {
          "5": 51800,
          "7": 20678,
          "11": 4496,
          "8": 634,
          "4": 2
        },
        "14": {
          "14": 65652,
          "6": 12410,
          "0": 256,
          "4": 2
        },
        "4": {
          "4": 76886,
          "11": 888,
          "6": 78,
          "10": 2
        },
        "11": {
          "11": 57174,
          "4": 6574,
          "7": 13490,
          "5": 916
        },
        "10": {
          "4": 15842,
          "11": 25334,
          "6": 7060,
          "7": 17040,
          "5": 7338,
          "14": 4998
        },
        "9": {
          "9": 77560,
          "15": 388
        },
        "0": {
          "0": 50268,
          "14": 3700,
          "11": 9192,
          "7": 798,
          "4": 12508,
          "6": 1554,
          "5": 54
        },
        "12": {
          "12": 76888,
          "1": 482,
          "8": 4
        },
        "3": {
          "13": 15778,
          "3": 60208,
          "1": 2060,
          "2": 54
        }
      }
    },
    "per_domain_accuracy": {
      "2": {
        "accuracy": 0.6947083333333334,
        "source?": true
      }
    }
  },
  "history": {
    "epoch_indices": [
      1,
      2,
      3,
      4,
      5,
      6,
      7,
      8,
      9,
      10,
      11,
      12,
      13,
      14,
      15,
      16,
      17,
      18,
      19,
      20,
      21,
      22,
      23,
      24,
      25,
      26,
      27,
      28,
      29,
      30,
      31,
      32,
      33,
      34,
      35,
      36,
      37,
      38,
      39,
      40,
      41,
      42,
      43,
      44,
      45,
      46,
      47,
      48,
      49,
      50,
      51,
      52,
      53,
      54,
      55,
      56,
      57,
      58,
      59,
      60,
      61,
      62,
      63,
      64,
      65,
      66,
      67,
      68,
      69,
      70,
      71,
      72,
      73,
      74,
      75,
      76,
      77,
      78,
      79,
      80,
      81,
      82,
      83,
      84,
      85,
      86,
      87,
      88,
      89,
      90,
      91,
      92,
      93,
      94,
      95,
      96,
      97,
      98,
      99,
      100,
      101,
      102,
      103,
      104,
      105,
      106,
      107,
      108,
      109,
      110,
      111,
      112,
      113,
      114,
      115,
      116,
      117,
      118,
      119,
      120,
      121,
      122,
      123,
      124,
      125,
      126,
      127,
      128,
      129,
      130,
      131,
      132,
      133,
      134,
      135,
      136,
      137,
      138,
      139,
      140,
      141,
      142,
      143,
      144,
      145,
      146,
      147,
      148,
      149,
      150,
      151,
      152,
      153,
      154,
      155,
      156,
      157,
      158,
      159,
      160,
      161,
      162,
      163,
      164,
      165,
      166,
      167,
      168,
      169,
      170,
      171,
      172,
      173,
      174,
      175,
      176,
      177,
      178,
      179,
      180,
      181,
      182,
      183,
      184,
      185,
      186,
      187
    ],
    "train_label_loss": [
      1.977873047346597,
      1.7436610023896773,
      1.689934856414795,
      1.6347912184117914,
      1.5934699728200723,
      1.5680435881667085,
      1.54642216194069,
      1.5273543785325774,
      1.5110318226342674,
      1.4950330907800695,
      1.4811679273332867,
      1.4673804364152008,
      1.4553135428795447,
      1.4415124815217741,
      1.4291425913297213,
      1.4180414556042178,
      1.4069379409328922,
      1.3970470128216586,
      1.388227438203581,
      1.379416225035112,
      1.3714726021316026,
      1.3638076600504445,
      1.3565280183750195,
      1.3503556251945077,
      1.344866926245637,
      1.3391134597442962,
      1.3341266653983148,
      1.32961974970849,
      1.3248545345788474,
      1.3206298817330664,
      1.316872438116388,
      1.313412802706708,
      1.309243183680943,
      1.304891375877045,
      1.2993482712336948,
      1.294314621757675,
      1.2874144189121959,
      1.2812001831243327,
      1.275600272817926,
      1.270570174080985,
      1.2646190881519528,
      1.2593298603938177,
      1.2535636264989665,
      1.247566151514158,
      1.2420806010214838,
      1.2368492035813383,
      1.229883369906918,
      1.2251735095034588,
      1.2203619599289945,
      1.215759097618061,
      1.211197761126927,
      1.2075694383998494,
      1.2009333717063233,
      1.1964594799817263,
      1.1926266251867943,
      1.1894457002210093,
      1.1868517394327855,
      1.1828184248379299,
      1.1808060029836802,
      1.1776813673291888,
      1.174930079963181,
      1.1726275028710837,
      1.1713587508673196,
      1.1688901397893716,
      1.1675200013275986,
      1.165105745252672,
      1.1625178948968322,
      1.1610119391640463,
      1.1578751240929404,
      1.1559313203319088,
      1.1531338417346662,
      1.1522328773907253,
      1.1503964464271461,
      1.1494723886762346,
      1.1468239992005484,
      1.1461981985280802,
      1.144005096409347,
      1.143744627910656,
      1.1421123948516427,
      1.1407540413678348,
      1.1385921971142947,
      1.1380214437233223,
      1.1365008178176461,
      1.1358905866539086,
      1.134322999912304,
      1.1329137872706403,
      1.1319900053412049,
      1.1310940235787696,
      1.1310712021942977,
      1.13097373181123,
      1.1295606146854358,
      1.1282984596870758,
      1.126719808463212,
      1.1271641218531263,
      1.1257142276292318,
      1.1250490436501555,
      1.1239702203247572,
      1.1238792839469491,
      1.1225785927667722,
      1.1218453696114676,
      1.1209341587863126,
      1.120843967794062,
      1.1198074129492372,
      1.1192824911180432,
      1.1187354759803185,
      1.1180221146436837,
      1.116871653839782,
      1.1162511726159317,
      1.115353016759013,
      1.114533168053889,
      1.114000275019761,
      1.1132972147228954,
      1.112397689960815,
      1.1118194400871193,
      1.1115142743823292,
      1.1103914315464734,
      1.1104952049674568,
      1.1098273419967064,
      1.10872299349439,
      1.1089121311208705,
      1.1076421099285503,
      1.1072797713384523,
      1.1074922155914726,
      1.1065554607883914,
      1.1052852335185794,
      1.1049707932472228,
      1.1045795021214329,
      1.1049832171345806,
      1.1038125916470538,
      1.10396371956186,
      1.1026183356190775,
      1.102480127947671,
      1.1013418660635477,
      1.1019272080306168,
      1.1012426708871192,
      1.1002735630706117,
      1.1001845738180391,
      1.099999018915407,
      1.0993348434626402,
      1.098977770265642,
      1.0982733712720347,
      1.0983663594696549,
      1.0973301037222474,
      1.0966231274971596,
      1.0960156401906695,
      1.0954051672442928,
      1.0966519362114289,
      1.0953370957217374,
      1.095425100185059,
      1.0961141184345706,
      1.0942779758998327,
      1.0943216841928252,
      1.0940315621711396,
      1.0931636847034916,
      1.093099344761817,
      1.0924808649702387,
      1.0923854163610018,
      1.091051327569144,
      1.0909503932785203,
      1.0915235921314785,
      1.0913460010591445,
      1.0916041625148647,
      1.091255945813525,
      1.0906574608834234,
      1.0903280244083196,
      1.0897431477452373,
      1.0887544628499628,
      1.0895736733688104,
      1.0885737464663747,
      1.0876043391122923,
      1.0889623025904644,
      1.0890759447590335,
      1.0883250597859477,
      1.087030971977737,
      1.086303230689122,
      1.087201792198223,
      1.0867752359568417,
      1.0872289406650668,
      1.086494323688549,
      1.086709998670515,
      1.0859973969616732,
      1.0854648383528323,
      1.085832132292318,
      1.0857327119491913,
      1.0853020279800498,
      1.0851075414772873,
      1.0850797605933724
    ],
    "val_label_loss": [
      1.7124504464586021,
      1.616959844239918,
      1.5368655856463438,
      1.486134801319723,
      1.4718239586112731,
      1.4344872453351603,
      1.4238508393081903,
      1.3887768184874663,
      1.3739725505357105,
      1.351334132993681,
      1.33019602841486,
      1.4679334291285233,
      1.3097767213312106,
      1.3152666073827297,
      1.2750275362897252,
      1.242353664596517,
      1.2344446149490425,
      1.236920897984133,
      1.2374047646276085,
      1.2375532901120831,
      1.1869259262984653,
      1.1870820867516547,
      1.166350955890768,
      1.1522201303090103,
      1.1690178303272631,
      1.1639533651178249,
      1.1351719256108466,
      1.1373452258657686,
      1.122242720939763,
      1.118329984032785,
      1.1150741830187023,
      1.1100198364922802,
      1.104008633670893,
      1.1034314649529493,
      1.1129038685457544,
      1.0998312363231446,
      1.0767946226905858,
      1.073315872238541,
      1.0677993037448348,
      1.0583118816396073,
      1.0546653107896606,
      1.05440062907898,
      1.0450355717400432,
      1.0413143591278395,
      1.0329871898894432,
      1.025297166457227,
      1.0305320236944977,
      1.0200933561254661,
      1.0101223205131424,
      1.0147841670309745,
      1.011405143217536,
      0.9954997671980462,
      0.9874867632117205,
      0.9972697626478463,
      0.9769076795926145,
      0.9780032861614149,
      0.9707754925687945,
      0.9680131913160476,
      0.9679329508733711,
      0.9623632669155474,
      0.9735593417074174,
      0.9604573170360333,
      0.983905069083831,
      0.9590875095671763,
      0.9534131477512816,
      0.9522672191421159,
      1.0066856959249466,
      0.9487500231563312,
      0.9485143664628389,
      0.9426398763556868,
      0.9710777079452737,
      0.935601784030955,
      0.9314965612336785,
      0.9268336616352604,
      0.9360801702987179,
      0.9275488439791509,
      0.9247065686710161,
      0.9259055933568984,
      0.9212247222001871,
      0.9279770975087489,
      0.9223533559031326,
      0.9216272594793787,
      0.9160708726870417,
      0.9151289386764915,
      0.9120677995134123,
      0.9105170675728339,
      0.9167612991536417,
      0.9222982660779413,
      0.915847717762189,
      0.9100148529670001,
      0.914436867679114,
      0.9169919607431992,
      0.9134748120401803,
      0.9105113511500151,
      0.9063358700744826,
      0.9118435905300466,
      0.9061813693588341,
      0.9174496851757572,
      0.9035796619664459,
      0.9035738226182154,
      0.9151479187463522,
      0.9027148813278192,
      0.899585792136251,
      0.9006235231328343,
      0.9022309809458656,
      0.9029771434028585,
      0.9116784283819503,
      0.8976840724751439,
      0.8934129303454179,
      0.8984203945182209,
      0.8939144578598092,
      0.8927799986462989,
      0.8951837105082135,
      0.8973764281619074,
      0.8940902685072698,
      0.8899233901813639,
      0.9215638023404629,
      0.8919804475657562,
      0.9097714702597987,
      0.8941218942232656,
      0.8874288124075866,
      0.8924495128699265,
      0.8924807651645341,
      0.8898166577966611,
      0.8919091375271153,
      0.9016304532458687,
      0.885228315125341,
      0.8876460271599451,
      0.8845754293656134,
      0.889995786330072,
      0.885525772447367,
      0.89980160600832,
      0.8971264919020095,
      0.8835926340484932,
      0.8843305270822446,
      0.8947994688722909,
      0.8875828207370392,
      0.880604491725723,
      0.8838060389687724,
      0.9027303762128844,
      0.8801994418833861,
      0.8837132667351004,
      0.8816859738517727,
      0.9237522755469134,
      0.8826048348994407,
      0.8808310030179497,
      0.8904211303559946,
      0.8782669141020708,
      0.8856625360138012,
      0.8772820529388149,
      0.8836188632704568,
      0.8774568074252197,
      0.8741696097745183,
      0.880502603477489,
      0.897608544539975,
      0.8992461750652088,
      0.8817343676403178,
      0.8814375841099283,
      0.876558471718609,
      0.8789890733921107,
      0.8886016698965193,
      0.8982108025349389,
      0.8724496387574788,
      0.8735314286615733,
      0.8784259756487642,
      0.8746197428050053,
      0.8784818206291105,
      0.8714345200713097,
      0.8710921048824664,
      0.8748585731402296,
      0.8702603862899753,
      0.8717173759422897,
      0.880704729428929,
      0.8758111534498088,
      0.8779696258391583,
      0.866536756413603,
      0.8853567543334898,
      0.8723202706654606,
      0.8723510992732373,
      0.8730745865635641,
      0.8812173374663425,
      0.8714148546213787,
      0.8705806642697422,
      0.8701625046816099,
      0.8697360112493012,
      0.8913448842653395,
      0.8695130024022798
    ]
  }
}